[
    {
        "title": "Test Title",
        "text": "Test text",
        "note_id": "1234"
    },
    {
        "title": "Title Two",
        "text": "Text two",
        "note_id": "gne1xu2lb7mj6xbztp65"
    },
    {
        "title": "Title Three",
        "text": "Text three",
        "note_id": "2h9kijo5wj7ofp7tgd6q"
    },
    {
        "title": "Note Four",
        "text": "Text Four",
        "note_id": "6p1b0428rzsobb160ex2"
    },
    {
        "title": "NEW TWO Test Title",
        "text": "NEW TWO Test text",
        "note_id": "cawvyacyq01n926s3gx4"
    },
    {
        "title": "NEW TWO Test Title",
        "text": "NEW TWO Test text",
        "note_id": "40owbsnp28j7q6or3imz"
    },
    {
        "title": "NEW TWO Test Title",
        "text": "NEW TWO Test text",
        "note_id": "9lzf2y3p9bkoy7znhtfp"
    },
    {
        "title": "NEW TWO Test Title",
        "text": "NEW TWO Test text",
        "note_id": "odbwjjgpeb6ryxta1ab9"
    },
    {
        "title": "NEW TWO Test Title",
        "text": "NEW TWO Test text",
        "note_id": "bysb2oyt186pnsuifcyf"
    },
    {
        "title": "NEW FIVE Test Title",
        "text": "NEW FIVE Test text",
        "note_id": "mjwzz3h40qj7dg1w5k4n"
    }
]